mspelling/__init__.py
mspelling/cli.py
mspelling/main.py
mspelling/results.py
mspelling/stimuli/audio/del.wav
mspelling/stimuli/audio/dos.wav
mspelling/stimuli/words/demo.csv
mspelling/ui/beginmessagescreen.kv
mspelling/ui/beginmessagescreen.py
mspelling/ui/elements.kv
mspelling/ui/endscreen.kv
mspelling/ui/endscreen.py
mspelling/ui/loginscreen.kv
mspelling/ui/loginscreen.py
mspelling/ui/mspelling.kv
mspelling/ui/restscreen.kv
mspelling/ui/restscreen.py
mspelling/ui/savescreen.kv
mspelling/ui/savescreen.py
mspelling/ui/spellingactivity.kv
mspelling/ui/spellingactivity.py
mspelling/ui/startscreen.kv
mspelling/ui/startscreen.py
mspelling/ui/welcomescreen.kv
mspelling/ui/welcomescreen.py
mspelling/worksheet.py
mspelling-0.2.2.dist-info/entry_points.txt
mspelling-0.2.2.dist-info/LICENSE
mspelling-0.2.2.dist-info/WHEEL
mspelling-0.2.2.dist-info/METADATA
mspelling-0.2.2.dist-info/RECORD
