Metadata-Version: 2.1
Name: mspelling
Version: 0.2.2
Summary: Measure of Spanish spelling skills
Home-page: https://github.com/mario-bermonti/mspelling
Keywords: mspelling
Author: Mario E. Bermonti Pérez
Author-email: mbermonti1132@gmail.com
Requires-Python: >=3.7.1,<3.11
Classifier: Development Status :: 2 - Pre-Alpha
Classifier: Intended Audience :: Developers
Classifier: License :: OSI Approved :: GNU General Public License v3 (GPLv3)
Classifier: Natural Language :: English
Classifier: Programming Language :: Python :: 3
Classifier: Programming Language :: Python :: 3.10
Classifier: Programming Language :: Python :: 3.7
Classifier: Programming Language :: Python :: 3.8
Classifier: Programming Language :: Python :: 3.9
Requires-Dist: Kivy (>=2.0.0,<3.0.0)
Requires-Dist: click (>=8.0.3,<9.0.0)
Requires-Dist: kivymd (>=0.104.2,<0.105.0)
Requires-Dist: numpy (>=1.21.5,<2.0.0)
Requires-Dist: pandas (>=1.3.5,<2.0.0)
Requires-Dist: xlrd (>=2.0.1,<3.0.0)
Project-URL: Bug Tracker, https://github.com/mario-bermonti/mspelling/issues
Project-URL: Documentation, https://mspelling.readthedocs.io
Project-URL: Repository, https://github.com/mario-bermonti/mspelling
